odoo8_addon_website_mail_snippet_table_edit-8.0.1.0.0.99.dev4-py2.7-nspkg.pth
odoo8_addon_website_mail_snippet_table_edit-8.0.1.0.0.99.dev4.dist-info/METADATA
odoo8_addon_website_mail_snippet_table_edit-8.0.1.0.0.99.dev4.dist-info/RECORD
odoo8_addon_website_mail_snippet_table_edit-8.0.1.0.0.99.dev4.dist-info/WHEEL
odoo8_addon_website_mail_snippet_table_edit-8.0.1.0.0.99.dev4.dist-info/namespace_packages.txt
odoo8_addon_website_mail_snippet_table_edit-8.0.1.0.0.99.dev4.dist-info/top_level.txt
odoo_addons/website_mail_snippet_table_edit/README.rst
odoo_addons/website_mail_snippet_table_edit/__init__.py
odoo_addons/website_mail_snippet_table_edit/__openerp__.py
odoo_addons/website_mail_snippet_table_edit/i18n/website_mail_snippet_table_edit.pot
odoo_addons/website_mail_snippet_table_edit/static/description/icon.png
odoo_addons/website_mail_snippet_table_edit/static/description/icon.svg
odoo_addons/website_mail_snippet_table_edit/views/snippets.xml
